LICENSE
README.md
setup.py
pystripe/__init__.py
pystripe/core.py
pystripe/lightsheet_correct.py
pystripe/raw.py
pystripe.egg-info/PKG-INFO
pystripe.egg-info/SOURCES.txt
pystripe.egg-info/dependency_links.txt
pystripe.egg-info/entry_points.txt
pystripe.egg-info/requires.txt
pystripe.egg-info/top_level.txt