Metadata-Version: 2.1
Name: pystripe
Version: 1.1.5
Summary: Stripe artifact filtering for SPIM images
Home-page: https://github.com/LifeCanvas-Technologies/pystripe
Author: LifeCanvas Technologies
License: MIT
Classifier: Development Status :: 3 - Alpha
Classifier: Programming Language :: Python :: 3.6
License-File: LICENSE
